pucktrick/__init__.py
pucktrick/duplicated.py
pucktrick/labels.py
pucktrick/missing.py
pucktrick/noisy.py
pucktrick/outliers.py
pucktrick/utils.py
pucktrick-0.5.1.dist-info/licenses/LICENCE
pucktrick-0.5.1.dist-info/METADATA
pucktrick-0.5.1.dist-info/WHEEL
pucktrick-0.5.1.dist-info/top_level.txt
pucktrick-0.5.1.dist-info/RECORD
