Metadata-Version: 2.4
Name: pucktrick
Version: 0.5.1
Summary: A python library for error generation in dataset for machine learning
Author-email: Andrea Maurino <andrea.maurino@unimib.it>
License: CC BY-NC 4.0
Project-URL: Homepage, https://github.com/andreamaurino/pucktrick
Classifier: Programming Language :: Python :: 3
Classifier: License :: Other/Proprietary License
Classifier: Operating System :: OS Independent
Requires-Python: >=3.6
License-File: LICENCE
Requires-Dist: numpy
Requires-Dist: pandas
Dynamic: license-file
